beetsplug/__init__.py
beetsplug/tagmod/__init__.py
beetsplug/tagmod/command/arguments.py
beetsplug/tagmod/command/options.py
beetsplug/tagmod/command/utilities.py
beetsplug/tagmod/configuration.py
beetsplug/tagmod/logging.py
beetsplug/tagmod/modification.py
beets_tagmod-0.1.0.dist-info/WHEEL
beets_tagmod-0.1.0.dist-info/METADATA
beets_tagmod-0.1.0.dist-info/RECORD
