Metadata-Version: 2.1
Name: beets-tagmod
Version: 0.1.0
Summary: A plugin for beets to modify media tags before they become written.
Home-page: https://github.com/weilbith/beets-tagmod
License: MIT
Author: Thore Weilbier
Author-email: thore@weilbier.net
Requires-Python: >=3.7,<4.0
Classifier: License :: OSI Approved :: MIT License
Classifier: Programming Language :: Python :: 3
Classifier: Programming Language :: Python :: 3.7
Requires-Dist: beets (>=1.4,<2.0)
Requires-Dist: confuse (>=1.0,<2.0)
Project-URL: Repository, https://github.com/weilbith/beets-tagmod
